personal_doc_library/__init__.py
personal_doc_library/cli.py
personal_doc_library/core/__init__.py
personal_doc_library/core/config.py
personal_doc_library/core/logging_config.py
personal_doc_library/core/shared_rag.py
personal_doc_library/core/timeout_handler.py
personal_doc_library/indexing/__init__.py
personal_doc_library/indexing/clean_pdfs.py
personal_doc_library/indexing/complete_indexing.py
personal_doc_library/indexing/execute_indexing.py
personal_doc_library/indexing/handle_large_pdf.py
personal_doc_library/indexing/index_large_pdf_detailed.py
personal_doc_library/indexing/index_monitor.py
personal_doc_library/indexing/index_specific.py
personal_doc_library/indexing/manage_failed_pdfs.py
personal_doc_library/indexing/monitor_indexing.py
personal_doc_library/loaders/email_loaders.py
personal_doc_library/loaders/emlx_loader.py
personal_doc_library/loaders/outlook_loader.py
personal_doc_library/monitoring/__init__.py
personal_doc_library/monitoring/monitor_web_enhanced.py
personal_doc_library/servers/__init__.py
personal_doc_library/servers/mcp_complete_server.py
personal_doc_library/utils/__init__.py
personal_doc_library/utils/check_indexing_status.py
personal_doc_library/utils/fallback_search.py
personal_doc_library/utils/find_unindexed.py
personal_doc_library/utils/fix_skipped_file.py
personal_doc_library/utils/index_lock.py
personal_doc_library/utils/ocr_manager.py
personal_doc_library/utils/show_config.py
personal_doc_library/utils/skip_and_continue.py
ragdex-0.2.3.dist-info/METADATA
ragdex-0.2.3.dist-info/WHEEL
ragdex-0.2.3.dist-info/entry_points.txt
ragdex-0.2.3.dist-info/licenses/LICENSE
ragdex-0.2.3.dist-info/RECORD
