Metadata-Version: 2.4
Name: ragdex
Version: 0.2.3
Summary: RAG-powered document indexing and search for MCP (Model Context Protocol)
Project-URL: Homepage, https://github.com/hpoliset/ragdex
Project-URL: Documentation, https://github.com/hpoliset/ragdex#readme
Project-URL: Issues, https://github.com/hpoliset/ragdex/issues
Project-URL: Repository, https://github.com/hpoliset/ragdex
Project-URL: Changelog, https://github.com/hpoliset/ragdex/releases
Author-email: hpoliset and contributors <hpoliset@users.noreply.github.com>
License: MIT License
License-File: LICENSE
Keywords: ai,chromadb,claude,documents,mcp,personal-library,rag,semantic-search
Classifier: Development Status :: 4 - Beta
Classifier: Intended Audience :: Developers
Classifier: Intended Audience :: Science/Research
Classifier: License :: OSI Approved :: MIT License
Classifier: Operating System :: MacOS
Classifier: Operating System :: POSIX :: Linux
Classifier: Programming Language :: Python :: 3
Classifier: Programming Language :: Python :: 3.10
Classifier: Programming Language :: Python :: 3.11
Classifier: Programming Language :: Python :: 3.12
Classifier: Topic :: Scientific/Engineering :: Artificial Intelligence
Classifier: Topic :: Software Development :: Libraries :: Python Modules
Classifier: Topic :: Text Processing :: Indexing
Requires-Python: >=3.10
Requires-Dist: beautifulsoup4>=4.11.0
Requires-Dist: chromadb==0.4.22
Requires-Dist: ebooklib>=0.18
Requires-Dist: emlx>=1.0.0
Requires-Dist: flask==3.0.0
Requires-Dist: langchain-community==0.0.10
Requires-Dist: langchain==0.1.0
Requires-Dist: mobi>=0.3.3
Requires-Dist: numpy<2.0
Requires-Dist: openpyxl
Requires-Dist: pdfminer-six
Requires-Dist: platformdirs>=4.0.0
Requires-Dist: psutil==5.9.7
Requires-Dist: pypdf
Requires-Dist: pypdf2==3.0.1
Requires-Dist: python-docx>=1.1.0
Requires-Dist: python-dotenv==1.0.0
Requires-Dist: sentence-transformers>=2.2.2
Requires-Dist: watchdog>=3.0.0
Provides-Extra: document-processing
Requires-Dist: pypandoc==1.12; extra == 'document-processing'
Requires-Dist: unstructured==0.11.5; extra == 'document-processing'
Provides-Extra: services
Requires-Dist: python-daemon>=3.0; extra == 'services'
